freshrss_mcp/__init__.py
freshrss_mcp/client.py
freshrss_mcp/models.py
freshrss_mcp/server.py
freshrss_mcp-0.2.0.dist-info/METADATA
freshrss_mcp-0.2.0.dist-info/WHEEL
freshrss_mcp-0.2.0.dist-info/entry_points.txt
freshrss_mcp-0.2.0.dist-info/RECORD
