Metadata-Version: 2.4
Name: freshrss-mcp
Version: 0.2.0
Summary: A Model Context Protocol server for FreshRSS RSS reader
Project-URL: Homepage, https://github.com/yourusername/freshrss-mcp
Project-URL: Repository, https://github.com/yourusername/freshrss-mcp
Project-URL: Issues, https://github.com/yourusername/freshrss-mcp/issues
Author: FreshRSS MCP Contributors
License-Expression: MIT
Keywords: feed-reader,freshrss,mcp,model-context-protocol,rss
Classifier: Development Status :: 3 - Alpha
Classifier: Intended Audience :: Developers
Classifier: License :: OSI Approved :: MIT License
Classifier: Programming Language :: Python :: 3
Classifier: Programming Language :: Python :: 3.9
Classifier: Programming Language :: Python :: 3.10
Classifier: Programming Language :: Python :: 3.11
Classifier: Programming Language :: Python :: 3.12
Requires-Python: >=3.9
Requires-Dist: aiohttp>=3.8.0
Requires-Dist: mcp>=1.0.0
Requires-Dist: pydantic>=2.0.0
Requires-Dist: python-dotenv>=1.0.0
Requires-Dist: typing-extensions>=4.8.0
Provides-Extra: dev
Requires-Dist: black>=23.0.0; extra == 'dev'
Requires-Dist: pytest-asyncio>=0.21.0; extra == 'dev'
Requires-Dist: pytest-cov>=4.0.0; extra == 'dev'
Requires-Dist: pytest>=7.0.0; extra == 'dev'
Requires-Dist: ruff>=0.1.0; extra == 'dev'
